error_boundary.py
setup.py
error_boundary.egg-info/PKG-INFO
error_boundary.egg-info/SOURCES.txt
error_boundary.egg-info/dependency_links.txt
error_boundary.egg-info/top_level.txt
tests/__init__.py
tests/test_error_boundary.py
tests/raven_stub/__init__.py
tests/raven_stub/contrib/__init__.py
tests/raven_stub/contrib/django/__init__.py
tests/raven_stub/contrib/django/raven_compat/__init__.py
tests/raven_stub/contrib/django/raven_compat/models.py