Metadata-Version: 1.1
Name: error-boundary
Version: 1.0.0
Summary: Error boundaries for Python
Home-page: https://github.com/cashlink/error-boundary
Author: Jonas Haag
Author-email: jonas@lophus.org
License: UNKNOWN
Platform: UNKNOWN
Classifier: Intended Audience :: Developers
Classifier: License :: OSI Approved :: ISC License (ISCL)
Classifier: Programming Language :: Python
Classifier: Programming Language :: Python :: 3.4
Classifier: Programming Language :: Python :: 3.5
Classifier: Programming Language :: Python :: 3.6
